netrun/logging/__init__.py
netrun/logging/context.py
netrun/logging/correlation.py
netrun/logging/ecosystem.py
netrun/logging/logger.py
netrun/logging/processors.py
netrun/logging/py.typed
netrun/logging/formatters/__init__.py
netrun/logging/formatters/json_formatter.py
netrun/logging/integrations/__init__.py
netrun/logging/integrations/azure_insights.py
netrun/logging/middleware/__init__.py
netrun/logging/middleware/fastapi.py
netrun_logging/__init__.py
netrun_logging/formatters/__init__.py
netrun_logging/integrations/__init__.py
netrun_logging/middleware/__init__.py
netrun_logging/middleware/fastapi.py
netrun_logging-2.0.0.dist-info/METADATA
netrun_logging-2.0.0.dist-info/WHEEL
netrun_logging-2.0.0.dist-info/licenses/LICENSE
netrun_logging-2.0.0.dist-info/RECORD
