Metadata-Version: 2.4
Name: netrun-logging
Version: 2.0.0
Summary: Unified structured logging service with Azure App Insights integration and namespace packaging
Project-URL: Homepage, https://netrunsystems.com
Project-URL: Repository, https://github.com/netrun-services/netrun-logging
Project-URL: Documentation, https://netrun-logging.readthedocs.io
Project-URL: Changelog, https://github.com/netrun-services/netrun-logging/blob/main/CHANGELOG.md
Author-email: Daniel Garza <daniel@netrunsystems.com>
License: MIT
License-File: LICENSE
Keywords: azure,correlation-id,fastapi,logging,namespace,structured-logging
Classifier: Development Status :: 5 - Production/Stable
Classifier: Intended Audience :: Developers
Classifier: Programming Language :: Python :: 3
Classifier: Programming Language :: Python :: 3.9
Classifier: Programming Language :: Python :: 3.10
Classifier: Programming Language :: Python :: 3.11
Classifier: Programming Language :: Python :: 3.12
Classifier: Topic :: Software Development :: Libraries :: Python Modules
Classifier: Topic :: System :: Logging
Requires-Python: >=3.9
Requires-Dist: azure-monitor-opentelemetry>=1.0.0
Requires-Dist: fastapi>=0.100.0
Requires-Dist: python-json-logger>=2.0.0
Requires-Dist: structlog>=24.0.0
Provides-Extra: all
Requires-Dist: netrun-auth>=2.0.0; extra == 'all'
Requires-Dist: netrun-config>=2.0.0; extra == 'all'
Requires-Dist: netrun-errors>=2.0.0; extra == 'all'
Provides-Extra: auth
Requires-Dist: netrun-auth>=2.0.0; extra == 'auth'
Provides-Extra: config
Requires-Dist: netrun-config>=2.0.0; extra == 'config'
Provides-Extra: dev
Requires-Dist: bandit>=1.7.0; extra == 'dev'
Requires-Dist: mypy>=1.0.0; extra == 'dev'
Requires-Dist: pytest-asyncio>=0.21.0; extra == 'dev'
Requires-Dist: pytest-cov>=4.0.0; extra == 'dev'
Requires-Dist: pytest>=7.0.0; extra == 'dev'
Requires-Dist: ruff>=0.1.0; extra == 'dev'
Provides-Extra: errors
Requires-Dist: netrun-errors>=2.0.0; extra == 'errors'
